SigProfilerClusters/SigProfilerClusters.py
SigProfilerClusters/SigProfilerHotSpots.py
SigProfilerClusters/__init__.py
SigProfilerClusters/classifyFunctions.py
SigProfilerClusters/convertToVCF.py
SigProfilerClusters/hotspot.py
SigProfilerClusters/plottingFunctions.py
SigProfilerClusters/version.py
SigProfilerClusters-1.2.2.dist-info/LICENSE
SigProfilerClusters-1.2.2.dist-info/METADATA
SigProfilerClusters-1.2.2.dist-info/WHEEL
SigProfilerClusters-1.2.2.dist-info/top_level.txt
SigProfilerClusters-1.2.2.dist-info/RECORD
