Metadata-Version: 2.2
Name: SigProfilerClusters
Version: 1.2.2
Summary: SigProfilerClusters tool
Home-page: 
Author: Erik Bergstrom
Author-email: ebergstr@eng.ucsd.edu
License: UCSD
Requires-Python: >=3.9
License-File: LICENSE
Requires-Dist: matplotlib>=3.5
Requires-Dist: sigProfilerPlotting>=1.4.0
Requires-Dist: SigProfilerMatrixGenerator>=1.3.2
Requires-Dist: SigProfilerSimulator>=1.2.1
Requires-Dist: statsmodels>=0.9.0
Requires-Dist: scipy>=1.1.0
Requires-Dist: pandas>=2.0.0
Requires-Dist: numpy>=2.0.0
Requires-Dist: SigProfilerExtractor>=1.2.0
Requires-Dist: seaborn>=0.13.0
Dynamic: author
Dynamic: author-email
Dynamic: description
Dynamic: description-content-type
Dynamic: license
Dynamic: requires-dist
Dynamic: requires-python
Dynamic: summary
